pynzbgetapi
